README.md
setup.py
pyMHMuser/__init__.py
pyMHMuser/__main__.py
pyMHMuser/configs.py
pyMHMuser/exceptions.py
pyMHMuser/loader.py
pyMHMuser/version.py
pyMHMuser.egg-info/PKG-INFO
pyMHMuser.egg-info/SOURCES.txt
pyMHMuser.egg-info/dependency_links.txt
pyMHMuser.egg-info/requires.txt
pyMHMuser.egg-info/top_level.txt
pyMHMuser/_misc/__init__.py
pyMHMuser/_misc/_assistant.py
pyMHMuser/_misc/_decorators.py
pyMHMuser/_misc/_supporter.py
pyMHMuser/_misc/_wrappers.py
pyMHMuser/dB/__init__.py
pyMHMuser/dB/_core.py
pyMHMuser/dB/afk_db.py
pyMHMuser/dB/antiflood_db.py
pyMHMuser/dB/asst_fns.py
pyMHMuser/dB/asstcmd_db.py
pyMHMuser/dB/autoban_db.py
pyMHMuser/dB/blacklist_chat_db.py
pyMHMuser/dB/blacklist_db.py
pyMHMuser/dB/botchat_db.py
pyMHMuser/dB/broadcast_db.py
pyMHMuser/dB/ch_db.py
pyMHMuser/dB/dnd_db.py
pyMHMuser/dB/echo_db.py
pyMHMuser/dB/filestore_db.py
pyMHMuser/dB/filter_db.py
pyMHMuser/dB/forcesub_db.py
pyMHMuser/dB/gban_mute_db.py
pyMHMuser/dB/gcast_blacklist_db.py
pyMHMuser/dB/greetings_db.py
pyMHMuser/dB/logusers_db.py
pyMHMuser/dB/mute_db.py
pyMHMuser/dB/night_db.py
pyMHMuser/dB/notes_db.py
pyMHMuser/dB/nsfw_db.py
pyMHMuser/dB/pmpermit_db.py
pyMHMuser/dB/snips_db.py
pyMHMuser/dB/vc_sudos.py
pyMHMuser/dB/warn_db.py
pyMHMuser/functions/FastTelethon.py
pyMHMuser/functions/__init__.py
pyMHMuser/functions/admins.py
pyMHMuser/functions/executor.py
pyMHMuser/functions/gDrive.py
pyMHMuser/functions/google_image.py
pyMHMuser/functions/helper.py
pyMHMuser/functions/info.py
pyMHMuser/functions/misc.py
pyMHMuser/functions/tools.py
pyMHMuser/functions/ytdl.py
pyMHMuser/startup/BaseClient.py
pyMHMuser/startup/__init__.py
pyMHMuser/startup/_database.py
pyMHMuser/startup/_extra.py
pyMHMuser/startup/connections.py
pyMHMuser/startup/funcs.py
pyMHMuser/startup/loader.py
pyMHMuser/startup/utils.py