Metadata-Version: 2.1
Name: pyMHMuser
Version: 2022.3.20
Summary: A Secure and Powerful Python-Telethon Based Library For MHMuser Userbot.
Home-page: https://github.com/Dev-MHM/pyMHMuser
Author: MHMuser
Author-email: mohammadihussein.m@gmail.com
License: GNU AFFERO GENERAL PUBLIC LICENSE (v3)
Project-URL: Bug Tracker, https://github.com/Dev-MHM/pyMHMuser/issues
Project-URL: Documentation, https://MHMuser.tech
Project-URL: Source Code, https://github.com/Dev-MHM/pyMHMuser
Platform: UNKNOWN
Classifier: Programming Language :: Python :: 3
Classifier: Programming Language :: Python :: 3.8
Classifier: Programming Language :: Python :: 3.9
Classifier: Programming Language :: Python :: 3.10
Classifier: License :: OSI Approved :: GNU General Public License v3 (GPLv3)
Classifier: Operating System :: OS Independent
Requires-Python: >3.7, <3.11
